RobloxPyApi3/AccountInformation.py
RobloxPyApi3/Auth.py
RobloxPyApi3/Avatar.py
RobloxPyApi3/Captcha.py
RobloxPyApi3/Catalog.py
RobloxPyApi3/Check.png
RobloxPyApi3/Client.py
RobloxPyApi3/Enums.py
RobloxPyApi3/Errors.py
RobloxPyApi3/FriendsAPI.py
RobloxPyApi3/JoinGame.py
RobloxPyApi3/LeaveGame.py
RobloxPyApi3/MultiAccount.py
RobloxPyApi3/Place.py
RobloxPyApi3/PlacePropTypes.py
RobloxPyApi3/SessionUtilities.py
RobloxPyApi3/Test.py
RobloxPyApi3/Utilities.py
RobloxPyApi3/Version.py
RobloxPyApi3/__Changes__.py
RobloxPyApi3/__init__.py
RobloxPyApi3/friends.py
RobloxPyApi3/Place/CallMethods.py
RobloxPyApi3/Place/Instructions.py
RobloxPyApi3/Place/Place.py
RobloxPyApi3/Place/__init__.py
RobloxPyApi3/Place/rbxLua2py.py
RobloxPyApi3-2.0.7999221.dist-info/METADATA
RobloxPyApi3-2.0.7999221.dist-info/WHEEL
RobloxPyApi3-2.0.7999221.dist-info/top_level.txt
RobloxPyApi3-2.0.7999221.dist-info/RECORD
