Metadata-Version: 2.1
Name: RobloxPyApi3
Version: 2.0.7999221
Summary: RobloxPyApi3 is a Python API controller for Roblox, offering API wrapping, multi-account management, and more. Create and manage Roblox accounts and Places with ease. Thanks.
Author: pyProjects3 (github.com/pyProjects3)
License: MIT
Keywords: Roblox,Api,wrapper,Bot,Client,Automated,Account Management,rbx,Python3,Place automation,post requests,get requests,JSON,Authorization,Roblox Development
Classifier: Development Status :: 1 - Planning
Classifier: Intended Audience :: Developers
Classifier: Programming Language :: Python :: 3
Classifier: Operating System :: Microsoft :: Windows
Requires-Dist: requests
Requires-Dist: colorama
Requires-Dist: psutil
Requires-Dist: RobloxPyApi3Update
Requires-Dist: pyautogui
